[
  {
    "id": "k1bc152h",
    "name": "teste",
    "tag": "Geral",
    "imported_at": "2026-04-10",
    "history": [
      {
        "date": "10/04/2026 00:42",
        "duration": 30
      },
      {
        "date": "10/04/2026 00:58",
        "duration": 38
      },
      {
        "date": "10/04/2026 01:09",
        "duration": 31
      },
      {
        "date": "10/04/2026 01:14",
        "duration": 38
      },
      {
        "date": "10/04/2026 01:18",
        "duration": 31
      }
    ]
  }
]